dubborequests/__init__.py
dubborequests/api.py
dubborequests/config.py
dubborequests/util.py
dubborequests-0.9.4.dist-info/LICENSE
dubborequests-0.9.4.dist-info/METADATA
dubborequests-0.9.4.dist-info/WHEEL
dubborequests-0.9.4.dist-info/top_level.txt
dubborequests-0.9.4.dist-info/RECORD
