Metadata-Version: 2.1
Name: dubborequests
Version: 0.9.4
Summary: Telnet command test dubbo
Home-page: https://github.com/JokerChat/dubbo_requests
Author: fang
Author-email: 664616581@qq.com
License: MIT
Platform: UNKNOWN
Classifier: Programming Language :: Python :: 3
Classifier: License :: OSI Approved :: MIT License
Classifier: Operating System :: OS Independent
Requires-Python: >=3.9.0
License-File: LICENSE
Requires-Dist: kazoo
